{
    "model_id": 1730786084,
    "url": "https://market.yandex.ru/product/1730786084/spec?sku=100382852160",
    "product_name": "Набор MUHLE Intro Rytmo с чашей смола подставка, помазок, Т-образная бритва, черный",
    "category": "Красота",
    "subcategory": "Бритвы и лезвия",
    "prev_image": "https://avatars.mds.yandex.net/get-mpic/4599566/img_id2043068817627060113.jpeg/orig",
    "description": "Набор для бритья из четырех предметов: - безопасная бритва со сменным лезвием - помазок для бритья с натуральным барсучьим ворсом - подставка, хром - чаша для бритья, хром. Натуральный барсучий ворс - отличный выбор для любителей влажного бритья, предпочитающих эффект массажа перед процедурой бритья. Кисть из натурального ворса изготавливается механически. Ворс более мягкий, чем щетина кабана, но более жесткий, чем ворс категории Fine и, конечно, Silvertip. Цвет колеблется от коричневато-серого к черному.",
    "full_description": "Набор для бритья из четырех предметов: - безопасная бритва со сменным лезвием - помазок для бритья с натуральным барсучьим ворсом - подставка, хром - чаша для бритья, хром. Натуральный барсучий ворс - отличный выбор для любителей влажного бритья, предпочитающих эффект массажа перед процедурой бритья. Кисть из натурального ворса изготавливается механически. Ворс более мягкий, чем щетина кабана, но более жесткий, чем ворс категории Fine и, конечно, Silvertip. Цвет колеблется от коричневато-серого к черному.",
    "vendor": "MUHLE",
    "photos": [
        {
            "url": "https://avatars.mds.yandex.net/get-mpic/4599566/img_id2043068817627060113.jpeg/orig"
        },
        {
            "url": "https://avatars.mds.yandex.net/get-mpic/4561793/img_id6434969573561121117.jpeg/orig"
        },
        {
            "url": "https://avatars.mds.yandex.net/get-mpic/5303146/img_id8747844295697988671.jpeg/orig"
        }
    ],
    "video": null,
    "specifications": [
        {
            "category": "Общие характеристики",
            "name": "Тип",
            "value": "набор"
        },
        {
            "category": "Общие характеристики",
            "name": "Насадка Т-образного станка",
            "value": "закрытая"
        },
        {
            "category": "Общие характеристики",
            "name": "Материал ручки",
            "value": "смола"
        },
        {
            "category": "Общие характеристики",
            "name": "Материал кисти помазка",
            "value": "барсучий ворс"
        },
        {
            "category": "Общие характеристики",
            "name": "Дополнительная информация",
            "value": "подставка и чаша для бритья из хрома; высококачественная синтетическая смола"
        }
    ],
    "status": "OK"
}