{
    "model_id": 1868402971,
    "url": "https://market.yandex.ru/product/1868402971/spec?sku=100545142738",
    "product_name": "Weleda крем увлажняющий мужской, 30 мл/50 г",
    "category": "Красота",
    "subcategory": "Уход за лицом",
    "prev_image": "https://avatars.mds.yandex.net/get-mpic/5288781/img_id3720985509200951115.jpeg/orig",
    "description": "Натуральный крем быстро впитывается, отлично увлажняет и освежает лицо. Подходит для всех типов кожи, в том числе и для чувствительной. Ценные масла жожоба и кунжута в сочетании с экстрактами гамамелиса и корня алтея интенсивно питают и поддерживают естественный гидролипидный баланс эпидермиса. Природные воски защищают кожу от негативного воздействия внешних факторов. Кожа становится гладкой и эластичной. Композиция чистейших эфирных масел придает крему бодрящий аромат.",
    "full_description": "Натуральный крем быстро впитывается, отлично увлажняет и освежает лицо. Подходит для всех типов кожи, в том числе и для чувствительной. Ценные масла жожоба и кунжута в сочетании с экстрактами гамамелиса и корня алтея интенсивно питают и поддерживают естественный гидролипидный баланс эпидермиса. Природные воски защищают кожу от негативного воздействия внешних факторов. Кожа становится гладкой и эластичной. Композиция чистейших эфирных масел придает крему бодрящий аромат.",
    "vendor": "Weleda",
    "photos": [
        {
            "url": "https://avatars.mds.yandex.net/get-mpic/5288781/img_id3720985509200951115.jpeg/orig"
        },
        {
            "url": "https://avatars.mds.yandex.net/get-mpic/5319158/img_id1704117102937960141.jpeg/orig"
        },
        {
            "url": "https://avatars.mds.yandex.net/get-mpic/4519143/img_id3386286980854319940.jpeg/orig"
        },
        {
            "url": "https://avatars.mds.yandex.net/get-mpic/4289990/img_id8035941973919535091.jpeg/orig"
        },
        {
            "url": "https://avatars.mds.yandex.net/get-mpic/4012150/img_id1979530385256925263.jpeg/orig"
        },
        {
            "url": "https://avatars.mds.yandex.net/get-mpic/4119784/img_id7914225292296144859.jpeg/orig"
        },
        {
            "url": "https://avatars.mds.yandex.net/get-mpic/372220/img_id2372102491119459626.png/orig"
        },
        {
            "url": "https://avatars.mds.yandex.net/get-mpic/5352299/img_id5527430192437613405.jpeg/orig"
        },
        {
            "url": "https://avatars.mds.yandex.net/get-mpic/1883514/img_id3935721690231985648.jpeg/orig"
        },
        {
            "url": "https://avatars.mds.yandex.net/get-mpic/5177817/img_id3085612524363289561.jpeg/orig"
        },
        {
            "url": "https://avatars.mds.yandex.net/get-mpic/5279470/img_id1266166192872236383.jpeg/orig"
        },
        {
            "url": "https://avatars.mds.yandex.net/get-mpic/4249638/img_id8015588189433498098.jpeg/orig"
        },
        {
            "url": "https://avatars.mds.yandex.net/get-mpic/5159019/img_id7062357475556230676.jpeg/orig"
        },
        {
            "url": "https://avatars.mds.yandex.net/get-mpic/5236304/img_id6844511039389854604.jpeg/orig"
        },
        {
            "url": "https://avatars.mds.yandex.net/get-mpic/11906264/2a0000018d32a0cef85fadb14d86dfb4db84/orig"
        }
    ],
    "video": null,
    "specifications": [
        {
            "category": "Общие характеристики",
            "name": "Средство",
            "value": "крем"
        },
        {
            "category": "Общие характеристики",
            "name": "Тип кожи",
            "value": "для всех типов"
        },
        {
            "category": "Общие характеристики",
            "name": "Потребности кожи",
            "value": "чувствительная"
        },
        {
            "category": "Общие характеристики",
            "name": "Эффект",
            "value": "питание, повышение упругости, увлажнение"
        },
        {
            "category": "Общие характеристики",
            "name": "Антивозрастное",
            "value": "да"
        },
        {
            "category": "Общие характеристики",
            "name": "Активный ингредиент",
            "value": "глицерин"
        },
        {
            "category": "Общие характеристики",
            "name": "Не содержит",
            "value": "искусственные консерванты, искусственные красители, отдушки"
        },
        {
            "category": "Общие характеристики",
            "name": "Масла и экстракты",
            "value": "кунжутное масло, масло жожоба, экстракт корня алтея"
        },
        {
            "category": "Общие характеристики",
            "name": "Состав",
            "value": "вода, масло жожоба, кунжутное масло, спирт, экстракт гамамелиса, глицерин, глицерин жирной кислоты, гидролизованный пчелиный воск, вулканическая глина, экстракт корня алтея, ксантан, пчелиный воск, карнаубский воск, мыло из пчелиного воска, каррагинан, смесь натуральных эфирных масел"
        },
        {
            "category": "Общие характеристики",
            "name": "Способ применения",
            "value": "крем нанести на кожу и нежно вмассировать"
        },
        {
            "category": "Дополнительно",
            "name": "Срок годности",
            "value": "1096 дн."
        }
    ],
    "status": "OK"
}