{
    "model_id": 507456270,
    "url": "https://market.yandex.ru/product/507456270/spec?sku=100707910145",
    "product_name": "Шаветт KayPro Опасная бритва Beard Club",
    "category": "Красота",
    "subcategory": "Бритвы и лезвия",
    "prev_image": "https://avatars.mds.yandex.net/get-mpic/4012413/img_id5035974480984342636.jpeg/orig",
    "description": "Бритва опасная Beard Club — это отличный выбор для мужчин, предпочитающих классику и стильные аксессуары. Лаконичный сдержанный дизайн в сочетании с качественным исполнением смотрится эффектно и дорого. Опасное лезвие из японской стали гарантирует непревзойденное качество бритья. Надежная ручка из промасленного дуба удобно ложится в ладонь и не боится воздействия влаги.",
    "full_description": "Бритва опасная Beard Club — это отличный выбор для мужчин, предпочитающих классику и стильные аксессуары. Лаконичный сдержанный дизайн в сочетании с качественным исполнением смотрится эффектно и дорого. Опасное лезвие из японской стали гарантирует непревзойденное качество бритья. Надежная ручка из промасленного дуба удобно ложится в ладонь и не боится воздействия влаги.",
    "vendor": "KayPro",
    "photos": [
        {
            "url": "https://avatars.mds.yandex.net/get-mpic/4012413/img_id5035974480984342636.jpeg/orig"
        },
        {
            "url": "https://avatars.mds.yandex.net/get-mpic/5216590/img_id1147815639391160620.jpeg/orig"
        }
    ],
    "video": null,
    "specifications": [
        {
            "category": "Общие характеристики",
            "name": "Тип",
            "value": "шаветт"
        }
    ],
    "status": "OK"
}