{
    "model_id": 1874255193,
    "url": "https://market.yandex.ru/product/1874255193/spec?sku=100874203181",
    "product_name": "Uriage гель очищающий Hyseac, 500 мл",
    "category": "Красота",
    "subcategory": "Средства для умывания",
    "prev_image": "https://avatars.mds.yandex.net/get-mpic/4867510/img_id1450119783450572112.jpeg/orig",
    "description": "Форма выпуска и упаковка Гель для лица флакон-помпа, 500 мл Состав AQUA (WATER, URIAGE THERMAL WATER), SODIUM LAURETH SULFATE, PEG-80 GLYCERYL COCOATE, SODIUM COCOAMPHOACETATE, PPG-2 HYDROXYETHYL COCAMIDE, COCO-GLUCOSIDE, GLYCERYL OLEATE, SODIUM LAURETH-8 SULFATE, SODIUM METHYL COCOYL TAURATE, GLYCINE, SODIUM CHLORIDE, PPG-2 HYDROXYETHYL COCO/ISOSTEARAMIDE, CITRIC ACID, PIROCTONE OLAMINE, SODIUM OLETH SULFATE, MAGNESIUM LAURETH SULFATE, PARFUM (FRAGRANCE)",
    "full_description": "Форма выпуска и упаковка Гель для лица флакон-помпа, 500 мл Состав AQUA (WATER, URIAGE THERMAL WATER), SODIUM LAURETH SULFATE, PEG-80 GLYCERYL COCOATE, SODIUM COCOAMPHOACETATE, PPG-2 HYDROXYETHYL COCAMIDE, COCO-GLUCOSIDE, GLYCERYL OLEATE, SODIUM LAURETH-8 SULFATE, SODIUM METHYL COCOYL TAURATE, GLYCINE, SODIUM CHLORIDE, PPG-2 HYDROXYETHYL COCO/ISOSTEARAMIDE, CITRIC ACID, PIROCTONE OLAMINE, SODIUM OLETH SULFATE, MAGNESIUM LAURETH SULFATE, PARFUM (FRAGRANCE)",
    "vendor": "Uriage",
    "photos": [
        {
            "url": "https://avatars.mds.yandex.net/get-mpic/4867510/img_id1450119783450572112.jpeg/orig"
        },
        {
            "url": "https://avatars.mds.yandex.net/get-mpic/5267253/img_id6240861855897017162.jpeg/orig"
        },
        {
            "url": "https://avatars.mds.yandex.net/get-mpic/4525599/img_id1325706284407589978.jpeg/orig"
        },
        {
            "url": "https://avatars.mds.yandex.net/get-mpic/5251231/img_id1144519047691961602.jpeg/orig"
        },
        {
            "url": "https://avatars.mds.yandex.net/get-mpic/1970506/img_id697761050426923912.jpeg/orig"
        },
        {
            "url": "https://avatars.mds.yandex.net/get-mpic/5236090/2a0000018a4f07d718882a006a02f9512cf0/orig"
        },
        {
            "url": "https://avatars.mds.yandex.net/get-mpic/1767151/2a0000018a4f07ebea5931eada101d21f977/orig"
        },
        {
            "url": "https://avatars.mds.yandex.net/get-mpic/5279470/2a0000018a4f07e8e5aef076237cd36a7b15/orig"
        },
        {
            "url": "https://avatars.mds.yandex.net/get-mpic/4012413/2a0000018a4f07edd3215ac45e81c97aff5d/orig"
        },
        {
            "url": "https://avatars.mds.yandex.net/get-mpic/1554397/img_id734778894080717584.jpeg/orig"
        }
    ],
    "video": null,
    "specifications": [
        {
            "category": "Общие характеристики",
            "name": "Линейка",
            "value": "Hyseac"
        },
        {
            "category": "Общие характеристики",
            "name": "Средство",
            "value": "гель"
        },
        {
            "category": "Общие характеристики",
            "name": "Тип кожи",
            "value": "для всех типов, жирная, комбинированная, нормальная"
        },
        {
            "category": "Общие характеристики",
            "name": "Потребности кожи",
            "value": "акне, проблемная"
        },
        {
            "category": "Общие характеристики",
            "name": "Назначение",
            "value": "для снятия макияжа, для умывания, лицо, очищение"
        },
        {
            "category": "Общие характеристики",
            "name": "Особенности",
            "value": "гипоаллергенное"
        },
        {
            "category": "Общие характеристики",
            "name": "Эффект",
            "value": "матирование, от черных точек, очищение, подсушивание воспалений, себорегуляция, снятие воспалений, сужение пор, увлажнение"
        },
        {
            "category": "Общие характеристики",
            "name": "Не содержит",
            "value": "мыло, парабены, спирт"
        },
        {
            "category": "Общие характеристики",
            "name": "Активный ингредиент",
            "value": "гликолевая кислота, глицерин, фруктовые кислоты"
        },
        {
            "category": "Общие характеристики",
            "name": "Масла и экстракты",
            "value": "экстракт кипрея"
        },
        {
            "category": "Общие характеристики",
            "name": "Возраст",
            "value": "12+"
        },
        {
            "category": "Общие характеристики",
            "name": "Страна бренда",
            "value": "Франция"
        },
        {
            "category": "Общие характеристики",
            "name": "Способ применения",
            "value": "вспенить небольшую дозу геля в ладонях, нанести на влажную кожу лица (кроме контура глаз), тела (при необходимости) и слегка помассировать, оставить на 2 минуты и обильно смыть водой, аккуратно удалить остатки влаги."
        },
        {
            "category": "Общие характеристики",
            "name": "Состав",
            "value": "aqua, uriage thermal spring water, sodium laureth sulfate, peg-80 glyceryl cocate, sodium cocoamphoacetate, ppg-2 hydroxyethyl cocamide, coco-glucoside, glyceryl oleate, sodium laureth-8 sulfate, sodium methyl cocyl taurate, glycine, sodium chloride, peg-2 hydroxyethyl coco-isostearamide, citric acid, piroctone olamine, sodium oleth sulfate, magnesium laureth sulfate, parfum, magnesium laureth-8 sulfate, epilobium angustifolium extract, phenoxyethanol, sodium metabisulfite"
        },
        {
            "category": "Дополнительно",
            "name": "Срок годности",
            "value": "1096 дн."
        }
    ],
    "status": "OK"
}